[
  {
    "ano": 2020,
    "area_total": 44193,
    "desmatado": 578.2,
    "vegetacao_natural": 41197.5,
    "nao_vegetacao_natural": 589.1,
    "hidrografia": 1828.2,
    "nome_municipio": "Borba"
  },
  {
    "ano": 2014,
    "area_total": 44193,
    "desmatado": 542.1,
    "vegetacao_natural": 41233.6,
    "nao_vegetacao_natural": 589.1,
    "hidrografia": 1828.2,
    "nome_municipio": "Borba"
  },
  {
    "ano": 2019,
    "area_total": 44193,
    "desmatado": 565.9,
    "vegetacao_natural": 41209.8,
    "nao_vegetacao_natural": 589.1,
    "hidrografia": 1828.2,
    "nome_municipio": "Borba"
  },
  {
    "ano": 2009,
    "area_total": 44193,
    "desmatado": 514.5,
    "vegetacao_natural": 41261.2,
    "nao_vegetacao_natural": 589.1,
    "hidrografia": 1828.2,
    "nome_municipio": "Borba"
  },
  {
    "ano": 2022,
    "area_total": 44193,
    "desmatado": 631.3,
    "vegetacao_natural": 41144.4,
    "nao_vegetacao_natural": 589.1,
    "hidrografia": 1828.2,
    "nome_municipio": "Borba"
  },
  {
    "ano": 2002,
    "area_total": 44193,
    "desmatado": 472.0,
    "vegetacao_natural": 41303.7,
    "nao_vegetacao_natural": 589.1,
    "hidrografia": 1828.2,
    "nome_municipio": "Borba"
  },
  {
    "ano": 2015,
    "area_total": 44193,
    "desmatado": 546.2,
    "vegetacao_natural": 41229.5,
    "nao_vegetacao_natural": 589.1,
    "hidrografia": 1828.2,
    "nome_municipio": "Borba"
  },
  {
    "ano": 2016,
    "area_total": 44193,
    "desmatado": 547.8,
    "vegetacao_natural": 41227.9,
    "nao_vegetacao_natural": 589.1,
    "hidrografia": 1828.2,
    "nome_municipio": "Borba"
  },
  {
    "ano": 2003,
    "area_total": 44193,
    "desmatado": 480.6,
    "vegetacao_natural": 41295.1,
    "nao_vegetacao_natural": 589.1,
    "hidrografia": 1828.2,
    "nome_municipio": "Borba"
  },
  {
    "ano": 2021,
    "area_total": 44193,
    "desmatado": 593.1,
    "vegetacao_natural": 41182.6,
    "nao_vegetacao_natural": 589.1,
    "hidrografia": 1828.2,
    "nome_municipio": "Borba"
  },
  {
    "ano": 2013,
    "area_total": 44193,
    "desmatado": 539.7,
    "vegetacao_natural": 41236.0,
    "nao_vegetacao_natural": 589.1,
    "hidrografia": 1828.2,
    "nome_municipio": "Borba"
  },
  {
    "ano": 2010,
    "area_total": 44193,
    "desmatado": 523.6,
    "vegetacao_natural": 41252.1,
    "nao_vegetacao_natural": 589.1,
    "hidrografia": 1828.2,
    "nome_municipio": "Borba"
  },
  {
    "ano": 2018,
    "area_total": 44193,
    "desmatado": 555.2,
    "vegetacao_natural": 41220.5,
    "nao_vegetacao_natural": 589.1,
    "hidrografia": 1828.2,
    "nome_municipio": "Borba"
  },
  {
    "ano": 2007,
    "area_total": 44193,
    "desmatado": 503.4,
    "vegetacao_natural": 41272.3,
    "nao_vegetacao_natural": 589.1,
    "hidrografia": 1828.2,
    "nome_municipio": "Borba"
  },
  {
    "ano": 2005,
    "area_total": 44193,
    "desmatado": 500.6,
    "vegetacao_natural": 41275.1,
    "nao_vegetacao_natural": 589.1,
    "hidrografia": 1828.2,
    "nome_municipio": "Borba"
  },
  {
    "ano": 2004,
    "area_total": 44193,
    "desmatado": 489.5,
    "vegetacao_natural": 41286.2,
    "nao_vegetacao_natural": 589.1,
    "hidrografia": 1828.2,
    "nome_municipio": "Borba"
  },
  {
    "ano": 2000,
    "area_total": 44193,
    "desmatado": 465.1,
    "vegetacao_natural": 41310.6,
    "nao_vegetacao_natural": 589.1,
    "hidrografia": 1828.2,
    "nome_municipio": "Borba"
  },
  {
    "ano": 2008,
    "area_total": 44193,
    "desmatado": 511.9,
    "vegetacao_natural": 41263.8,
    "nao_vegetacao_natural": 589.1,
    "hidrografia": 1828.2,
    "nome_municipio": "Borba"
  },
  {
    "ano": 2006,
    "area_total": 44193,
    "desmatado": 502.3,
    "vegetacao_natural": 41273.4,
    "nao_vegetacao_natural": 589.1,
    "hidrografia": 1828.2,
    "nome_municipio": "Borba"
  },
  {
    "ano": 2017,
    "area_total": 44193,
    "desmatado": 551.2,
    "vegetacao_natural": 41224.5,
    "nao_vegetacao_natural": 589.1,
    "hidrografia": 1828.2,
    "nome_municipio": "Borba"
  },
  {
    "ano": 2011,
    "area_total": 44193,
    "desmatado": 535.3,
    "vegetacao_natural": 41240.4,
    "nao_vegetacao_natural": 589.1,
    "hidrografia": 1828.2,
    "nome_municipio": "Borba"
  },
  {
    "ano": 2012,
    "area_total": 44193,
    "desmatado": 537.3,
    "vegetacao_natural": 41238.4,
    "nao_vegetacao_natural": 589.1,
    "hidrografia": 1828.2,
    "nome_municipio": "Borba"
  },
  {
    "ano": 2001,
    "area_total": 44193,
    "desmatado": 468.7,
    "vegetacao_natural": 41307.0,
    "nao_vegetacao_natural": 589.1,
    "hidrografia": 1828.2,
    "nome_municipio": "Borba"
  }
]