{
  "id": "envira",
  "nome": "Envira",
  "detalhe": {
    "2012": {
      "2": {
        "num_diarios": 5,
        "num_licitacao": 6
      },
      "resumo": {
        "num_diarios": 76,
        "num_licitacao": 70
      },
      "3": {
        "num_diarios": 13,
        "num_licitacao": 22
      },
      "4": {
        "num_diarios": 11,
        "num_licitacao": 18
      },
      "5": {
        "num_diarios": 5,
        "num_licitacao": 6
      },
      "6": {
        "num_diarios": 14,
        "num_licitacao": 10
      },
      "7": {
        "num_diarios": 8,
        "num_licitacao": 4
      },
      "8": {
        "num_diarios": 5,
        "num_licitacao": 2
      },
      "9": {
        "num_diarios": 3
      },
      "10": {
        "num_diarios": 3
      },
      "11": {
        "num_diarios": 4,
        "num_licitacao": 2
      },
      "12": {
        "num_diarios": 5
      }
    },
    "2013": {
      "1": {
        "num_diarios": 8
      },
      "resumo": {
        "num_diarios": 107,
        "num_licitacao": 132
      },
      "2": {
        "num_diarios": 8,
        "num_licitacao": 4
      },
      "3": {
        "num_diarios": 11,
        "num_licitacao": 2
      },
      "4": {
        "num_diarios": 9,
        "num_licitacao": 6
      },
      "5": {
        "num_diarios": 11,
        "num_licitacao": 20
      },
      "6": {
        "num_diarios": 8,
        "num_licitacao": 22
      },
      "7": {
        "num_diarios": 8,
        "num_licitacao": 28
      },
      "8": {
        "num_diarios": 15,
        "num_licitacao": 16
      },
      "9": {
        "num_diarios": 7,
        "num_licitacao": 6
      },
      "10": {
        "num_diarios": 6,
        "num_licitacao": 10
      },
      "11": {
        "num_diarios": 4
      },
      "12": {
        "num_diarios": 12,
        "num_licitacao": 18
      }
    },
    "2014": {
      "1": {
        "num_diarios": 7,
        "num_licitacao": 4
      },
      "resumo": {
        "num_diarios": 91,
        "num_licitacao": 132
      },
      "2": {
        "num_diarios": 10,
        "num_licitacao": 20
      },
      "3": {
        "num_diarios": 8,
        "num_licitacao": 2
      },
      "4": {
        "num_diarios": 7,
        "num_licitacao": 4
      },
      "5": {
        "num_diarios": 9,
        "num_licitacao": 12
      },
      "6": {
        "num_diarios": 12,
        "num_licitacao": 32
      },
      "7": {
        "num_diarios": 8,
        "num_licitacao": 28
      },
      "8": {
        "num_diarios": 9,
        "num_licitacao": 12
      },
      "9": {
        "num_diarios": 3
      },
      "10": {
        "num_diarios": 6,
        "num_licitacao": 8
      },
      "11": {
        "num_diarios": 7,
        "num_licitacao": 2
      },
      "12": {
        "num_diarios": 5,
        "num_licitacao": 8
      }
    },
    "2015": {
      "1": {
        "num_diarios": 8,
        "num_licitacao": 18
      },
      "resumo": {
        "num_diarios": 106,
        "num_licitacao": 164
      },
      "2": {
        "num_diarios": 7,
        "num_licitacao": 6
      },
      "3": {
        "num_diarios": 7,
        "num_licitacao": 10
      },
      "4": {
        "num_diarios": 8,
        "num_licitacao": 24
      },
      "5": {
        "num_diarios": 8,
        "num_licitacao": 4
      },
      "6": {
        "num_diarios": 11,
        "num_licitacao": 6
      },
      "7": {
        "num_diarios": 8,
        "num_licitacao": 24
      },
      "8": {
        "num_diarios": 13,
        "num_licitacao": 22
      },
      "9": {
        "num_diarios": 8,
        "num_licitacao": 12
      },
      "10": {
        "num_diarios": 11,
        "num_licitacao": 18
      },
      "11": {
        "num_diarios": 6,
        "num_licitacao": 2
      },
      "12": {
        "num_diarios": 11,
        "num_licitacao": 18
      }
    },
    "2016": {
      "1": {
        "num_diarios": 11,
        "num_licitacao": 24
      },
      "resumo": {
        "num_diarios": 111,
        "num_licitacao": 202
      },
      "2": {
        "num_diarios": 7,
        "num_licitacao": 8
      },
      "3": {
        "num_diarios": 11,
        "num_licitacao": 12
      },
      "4": {
        "num_diarios": 8,
        "num_licitacao": 14
      },
      "5": {
        "num_diarios": 11,
        "num_licitacao": 48
      },
      "6": {
        "num_diarios": 17,
        "num_licitacao": 30
      },
      "7": {
        "num_diarios": 12,
        "num_licitacao": 18
      },
      "8": {
        "num_diarios": 8,
        "num_licitacao": 14
      },
      "9": {
        "num_diarios": 6,
        "num_licitacao": 14
      },
      "10": {
        "num_diarios": 6,
        "num_licitacao": 10
      },
      "11": {
        "num_diarios": 8,
        "num_licitacao": 10
      },
      "12": {
        "num_diarios": 6
      }
    },
    "2017": {
      "1": {
        "num_diarios": 16,
        "num_licitacao": 26
      },
      "resumo": {
        "num_diarios": 153,
        "num_licitacao": 196
      },
      "2": {
        "num_diarios": 9,
        "num_licitacao": 10
      },
      "3": {
        "num_diarios": 11,
        "num_licitacao": 8
      },
      "4": {
        "num_diarios": 13,
        "num_licitacao": 14
      },
      "5": {
        "num_diarios": 15,
        "num_licitacao": 16
      },
      "6": {
        "num_diarios": 14,
        "num_licitacao": 20
      },
      "7": {
        "num_diarios": 17,
        "num_licitacao": 30
      },
      "8": {
        "num_diarios": 16,
        "num_licitacao": 32
      },
      "9": {
        "num_diarios": 15,
        "num_licitacao": 12
      },
      "10": {
        "num_diarios": 8,
        "num_licitacao": 4
      },
      "11": {
        "num_diarios": 9,
        "num_licitacao": 8
      },
      "12": {
        "num_diarios": 10,
        "num_licitacao": 16
      }
    },
    "2018": {
      "1": {
        "num_diarios": 14,
        "num_licitacao": 14
      },
      "resumo": {
        "num_diarios": 156,
        "num_licitacao": 204
      },
      "2": {
        "num_diarios": 9,
        "num_licitacao": 14
      },
      "3": {
        "num_diarios": 19,
        "num_licitacao": 12
      },
      "4": {
        "num_diarios": 16,
        "num_licitacao": 12
      },
      "5": {
        "num_diarios": 18,
        "num_licitacao": 42
      },
      "6": {
        "num_diarios": 11,
        "num_licitacao": 16
      },
      "7": {
        "num_diarios": 17,
        "num_licitacao": 22
      },
      "8": {
        "num_diarios": 16,
        "num_licitacao": 20
      },
      "9": {
        "num_diarios": 10,
        "num_licitacao": 10
      },
      "10": {
        "num_diarios": 9,
        "num_licitacao": 6
      },
      "11": {
        "num_diarios": 9,
        "num_licitacao": 16
      },
      "12": {
        "num_diarios": 8,
        "num_licitacao": 20
      }
    },
    "2019": {
      "1": {
        "num_diarios": 10,
        "num_licitacao": 12
      },
      "resumo": {
        "num_diarios": 164,
        "num_licitacao": 158
      },
      "2": {
        "num_diarios": 12,
        "num_licitacao": 10
      },
      "3": {
        "num_diarios": 14,
        "num_licitacao": 4
      },
      "4": {
        "num_diarios": 11,
        "num_licitacao": 8
      },
      "5": {
        "num_diarios": 19,
        "num_licitacao": 12
      },
      "6": {
        "num_diarios": 11,
        "num_licitacao": 2
      },
      "7": {
        "num_diarios": 16,
        "num_licitacao": 8
      },
      "8": {
        "num_diarios": 15,
        "num_licitacao": 12
      },
      "9": {
        "num_diarios": 13,
        "num_licitacao": 16
      },
      "10": {
        "num_diarios": 16,
        "num_licitacao": 12
      },
      "11": {
        "num_diarios": 12,
        "num_licitacao": 46
      },
      "12": {
        "num_diarios": 15,
        "num_licitacao": 16
      }
    },
    "2020": {
      "1": {
        "num_diarios": 11,
        "num_licitacao": 20
      },
      "resumo": {
        "num_diarios": 11,
        "num_licitacao": 20
      }
    }
  },
  "resumo": {
    "num_diarios": 975,
    "num_licitacao": 1278
  }
}